pysentation/__init__.py
pysentation/errors.py
pysentation/module.py
pysentation/package.py
pysentation/pysentation.py
pysentation/signs.py
pysentation-1.0.0.dist-info/LICENSE
pysentation-1.0.0.dist-info/METADATA
pysentation-1.0.0.dist-info/WHEEL
pysentation-1.0.0.dist-info/dependency_links.txt
pysentation-1.0.0.dist-info/entry_points.txt
pysentation-1.0.0.dist-info/top_level.txt
pysentation-1.0.0.dist-info/RECORD
