Metadata-Version: 2.1
Name: pysentation
Version: 1.0.0
Summary: pysentation is a CLI for displaying Python presentations.
Home-page: https://github.com/mimseyedi/pysentation
Author: mimseyedi
Author-email: mim.seyedi@gmail.com
License: GNU General Public License v3 (GPLv3)
Classifier: License :: OSI Approved :: GNU General Public License v3 (GPLv3)
Classifier: Programming Language :: Python :: 3
Classifier: Programming Language :: Python :: 3.11
Requires-Python: >=3.11
License-File: LICENSE
Requires-Dist: rich ==13.4.1
Requires-Dist: getkey ==0.6.5
Requires-Dist: click ==8.1.3
